botbuilder_discord/__init__.py
botbuilder_discord/connector.py
botbuilder_discord/session.py
botbuilder_discord/client/__init__.py
botbuilder_discord/client/client.py
botbuilder_discord/client/queue.py
botbuilder_discord/client/listener/__init__.py
botbuilder_discord/client/listener/listener.py
botbuilder_discord/client/sender/__init__.py
botbuilder_discord/client/sender/message.py
botbuilder_discord/client/sender/send_text_message.py
botbuilder_discord/client/sender/start_conversation_message.py
botbuilder_discord-0.1.0.dist-info/LICENSE
botbuilder_discord-0.1.0.dist-info/METADATA
botbuilder_discord-0.1.0.dist-info/WHEEL
botbuilder_discord-0.1.0.dist-info/top_level.txt
botbuilder_discord-0.1.0.dist-info/RECORD
